NBSapi/NBSapi.py
NBSapi/__init__.py
NBSapi/tests/GetVoices.py
NBSapi/tests/Save_to_audio_file.py
NBSapi/tests/SetVoice.py
NBSapi/tests/__init__.py
NBSapi/tests/control_speaking.py
NBSapi/tests/speak_wait.py
NBSapi/tests/speak_without_wait.py
NBSapi-0.6.dist-info/LICENSE.txt
NBSapi-0.6.dist-info/METADATA
NBSapi-0.6.dist-info/WHEEL
NBSapi-0.6.dist-info/top_level.txt
NBSapi-0.6.dist-info/RECORD
