Metadata-Version: 2.1
Name: NBSapi
Version: 0.6
Summary: a python library that helps you to control the sapi5 TTS
Home-page: https://github.com/baaziznasser/nbsapi
Download-URL: https://github.com/baaziznasser/nbsapi/archive/refs/tags/0.5.tar.gz
Author: nacer baaziz
Author-email: Nacer Baaziz <nacerbaaziz@ng-space.com>
License: GPL-3.0
Project-URL: Homepage, https://github.com/baaziznasser/nbsapi
Project-URL: Bug Tracker, https://github.com/baaziznasser/nbsapi/issues
Keywords: nbsapi,NBSapi,Sapi,tts,python text to speech,audio,screen reader,voices,sapi5,spvoice,text to speech,audio book
Classifier: Development Status :: 5 - Production/Stable
Classifier: Intended Audience :: Developers
Classifier: Topic :: Software Development :: Build Tools
Classifier: Programming Language :: Python :: 3
Classifier: License :: OSI Approved :: GNU Affero General Public License v3 or later (AGPLv3+)
Classifier: Operating System :: Microsoft :: Windows
Requires-Python: >=3
License-File: LICENSE.txt
Requires-Dist: comtypes
